{
  "description": "X11 terminal emulator with 256 colors",

  "columns": 80,
  "lines": 24,
  "colors": 256,
  "truecolor": true,
  "unicode": false,

  "bell": "\b",
  "clear": "\u001b[H\u001b[2J",
  "clearLine": "\u001b[G\u001b[2K",
  "reset": "\u001bc\u001b[!p\u001b?3;4l\u001b[4l\u001b>\u001b[m"
  "enterAlternateBuffer": "\u001b[?1049h",
  "exitAlternateBuffer": "\u001b[?1049l",
  "enterKeypad": "\u001b[?1h\u001b=",
  "exitKeypad": "\u001b[?1l\u001b>",
  "enterStatus": "\u001b]0;",
  "exitStatus": "\u0007",
  "enterAlternateCharset": "\u001b(0",
  "exitAlternateCharset": "\u001b(B",
  "enterPaste": "\u001b[?1049h",
  "exitPaste": "\u001b[?1049l",
  "beginPaste": "\u001b[200~",
  "endPaste": "\u001b[201~",

  "showCursor": "\u001b[?25h",
  "hideCursor": "\u001b[?25l",
  "alternateCharset": {
    "\u2518": "j",
    "\u2510": "k",
    "\u250c": "l",
    "\u2514": "m",
    "\u253c": "n",
    "\u2500": "q",
    "\u251c": "t",
    "\u2524": "u",
    "\u2534": "v",
    "\u252c": "w",
    "\u2502": "x"
  },
  "changeScrollRegion": "",

  "moveCursor": "\u001b[%i%p1%d;%p2%dH",
  "moveColumn": "\u001b[%i%p1%dG",
  "moveRow": "\u001b[%i%p1%dd",
  "cursorDown": "\u001b[%p1%dB",
  "cursorUp": "\u001b[%p1%dA",
  "cursorRight": "\u001b[%p1%dC",
  "cursorLeft": "\u001b[%p1%dD",
  "saveCursor": "\u001b7",
  "restoreCursor": "\u001b8",
  "requestCursor": "\u001b[6n",
  "reportCursor": "\u001b[%i%p1%d;%p2%dR",

  "enterBold": "\u001b[1m",
  "exitBold": "\u001b[22m",
  "enterDim": "\u001b[2m",
  "exitDim": "\u001b[22m",
  "enterReverse": "\u001b[7m",
  "exitReverse": "\u001b[27m",
  "enterUnderline": "\u001b[4m",
  "exitUnderline": "\u001b[24m",
  "enterItalic": "\u001b[3m",
  "exitItalic": "\u001b[23m",
  "enterConceal": "\u001b[8m",
  "exitConceal": "\u001b[28m",
  "enterBlink": "\u001b[5m",
  "exitBlink": "\u001b[25m",
  "enterStrikethrough": "\u001b[9m",
  "exitStrikethrough": "\u001b[29m",
  "resetAttribute": "\u001b(B\u001b[m",

  "setForeground": "\x1b[%?%p1%{8}%<%t3%p1%d%e%p1%{16}%<%t9%p1%{8}%-%d%e38;5;%p1%d%;m",
  "setBackground": "\x1b[%?%p1%{8}%<%t4%p1%d%e%p1%{16}%<%t10%p1%{8}%-%d%e48;5;%p1%d%;m",
  "setForegroundClear": "\x1b[39m",
  "setBackgroundClear": "\x1b[49m",
  "setForegroundTrue": "\x1b[38;2;%p1%d;%p2%d;%p3%dm",
  "setBackgroundTrue": "\x1b[48;2;%p1%d;%p2%d;%p3%dm",
  "setPair": "\x1b]4;%p1%d;rgb:%p2%X/%p3%X/%p4%X\x1b\\",
  "resetColor": "\u001b]104\u001b\\",

  "enterMouse": "",
  "exitMouse": "",
  "keyMouse": ""
}
